aliyunsdkdataphin_public/__init__.py
aliyunsdkdataphin_public/request/__init__.py
aliyunsdkdataphin_public/request/v20230630/AddDataServiceProjectMemberRequest.py
aliyunsdkdataphin_public/request/v20230630/AddProjectMemberRequest.py
aliyunsdkdataphin_public/request/v20230630/AddTenantMembersBySourceUserRequest.py
aliyunsdkdataphin_public/request/v20230630/AddTenantMembersRequest.py
aliyunsdkdataphin_public/request/v20230630/AddUserGroupMemberRequest.py
aliyunsdkdataphin_public/request/v20230630/ApplyDataServiceApiRequest.py
aliyunsdkdataphin_public/request/v20230630/ApplyDataServiceAppRequest.py
aliyunsdkdataphin_public/request/v20230630/CheckComputeSourceConnectivityByIdRequest.py
aliyunsdkdataphin_public/request/v20230630/CheckComputeSourceConnectivityRequest.py
aliyunsdkdataphin_public/request/v20230630/CheckDataSourceConnectivityByIdRequest.py
aliyunsdkdataphin_public/request/v20230630/CheckDataSourceConnectivityRequest.py
aliyunsdkdataphin_public/request/v20230630/CheckProjectHasDependencyRequest.py
aliyunsdkdataphin_public/request/v20230630/CheckResourcePermissionRequest.py
aliyunsdkdataphin_public/request/v20230630/CreateAdHocFileRequest.py
aliyunsdkdataphin_public/request/v20230630/CreateBatchTaskRequest.py
aliyunsdkdataphin_public/request/v20230630/CreateBizEntityRequest.py
aliyunsdkdataphin_public/request/v20230630/CreateBizUnitRequest.py
aliyunsdkdataphin_public/request/v20230630/CreateComputeSourceRequest.py
aliyunsdkdataphin_public/request/v20230630/CreateDataDomainRequest.py
aliyunsdkdataphin_public/request/v20230630/CreateDataServiceApiRequest.py
aliyunsdkdataphin_public/request/v20230630/CreateDataSourceRequest.py
aliyunsdkdataphin_public/request/v20230630/CreateDirectoryRequest.py
aliyunsdkdataphin_public/request/v20230630/CreateNodeSupplementRequest.py
aliyunsdkdataphin_public/request/v20230630/CreatePipelineNodeRequest.py
aliyunsdkdataphin_public/request/v20230630/CreateResourceRequest.py
aliyun_python_sdk_dataphin_public-1.0.13.dist-info/LICENSE
aliyun_python_sdk_dataphin_public-1.0.13.dist-info/METADATA
aliyun_python_sdk_dataphin_public-1.0.13.dist-info/WHEEL
aliyun_python_sdk_dataphin_public-1.0.13.dist-info/top_level.txt
aliyun_python_sdk_dataphin_public-1.0.13.dist-info/RECORD
